{"cameraMode":{"drawMode":0,"name":"Shaded","section":"Shading Mode"},"sceneLighting":true,"audioPlay":false,"sceneViewState":{"showFog":true,"showMaterialUpdate":false,"showSkybox":true,"showFlares":true,"showImageEffects":true,"showParticleSystems":true},"in2DMode":false,"pivot":{"x":0.6373474597930908,"y":2.670365333557129,"z":-0.8470284938812256},"rotation":{"x":0.2337302565574646,"y":-0.30716419219970705,"z":0.07810474187135697,"w":0.9191955327987671},"size":1.7615528106689454,"orthographic":false}